password_store/__init__.py
password_store/credentials.py
password_store-0.3.dist-info/DESCRIPTION.rst
password_store-0.3.dist-info/METADATA
password_store-0.3.dist-info/RECORD
password_store-0.3.dist-info/WHEEL
password_store-0.3.dist-info/metadata.json
password_store-0.3.dist-info/top_level.txt
