Metadata-Version: 2.0
Name: password-store
Version: 0.3
Summary: Password Store Wrapper
Home-page: https://github.com/jmcs/py-password-store
Author: João Santos
Author-email: jmcs@jsantos.eu
License: MIT License
Platform: UNKNOWN
Classifier: Programming Language :: Python
Classifier: Programming Language :: Python :: 3.5
Classifier: Development Status :: 4 - Beta
Classifier: Operating System :: OS Independent
Requires-Dist: pyyaml
